README.md
setup.py
rxd/__init__.py
rxd/app_manager.py
rxd/cmd.py
rxd/cmd_app.py
rxd/codex.py
rxd/daemonizers.py
rxd/messages.py
rxd/responder.py
rxd.egg-info/PKG-INFO
rxd.egg-info/SOURCES.txt
rxd.egg-info/dependency_links.txt
rxd.egg-info/entry_points.txt
rxd.egg-info/not-zip-safe
rxd.egg-info/requires.txt
rxd.egg-info/top_level.txt