Metadata-Version: 2.1
Name: rxd
Version: 0.0.21
Summary: A reactive application manager
Home-page: https://github.com/huyng/rxd
Author: Huy Nguyen
Author-email: 121183+huyng@users.noreply.github.com
Requires-Dist: Flask
Requires-Dist: Click
Requires-Dist: tabulate
Requires-Dist: pydantic
